staff_graded/__init__.py
staff_graded/staff_graded.py
staff_graded/static/README.txt
staff_graded/static/css/staff_graded.css
staff_graded/static/html/staff_graded.html
staff_graded/static/js/src/staff_graded.js
staff_graded_xblock-3.1.0.dist-info/LICENSE
staff_graded_xblock-3.1.0.dist-info/METADATA
staff_graded_xblock-3.1.0.dist-info/WHEEL
staff_graded_xblock-3.1.0.dist-info/entry_points.txt
staff_graded_xblock-3.1.0.dist-info/top_level.txt
staff_graded_xblock-3.1.0.dist-info/RECORD
